Workbook

Sheet Instructions
A1: MS Excel Practical Exam
A2: Total Questions: 30
A3: Difficulty Level: Medium
A4: Syllabus: Formulas, Logical Functions, Lookups, INDEX-MATCH, Pivot Tables & Charts, Data Analysis
A5: Attempt all questions using appropriate Excel tools/functions.

Sheet Sales_Data
A1: Order_ID | B1: Region | C1: Salesperson | D1: Product | E1: Quantity | F1: Unit_Price | G1: Sales_Date
A2: 301 | B2: North | C2: Amit | D2: Laptop | E2: 2 | F2: 45000 | G2: 05-01-2025
A3: 302 | B3: South | C3: Riya | D3: Mobile | E3: 5 | F3: 15000 | G3: 07-01-2025
A4: 303 | B4: East | C4: Kunal | D4: Tablet | E4: 3 | F4: 18000 | G4: 10-01-2025
A5: 304 | B5: West | C5: Neha | D5: Laptop | E5: 1 | F5: 45000 | G5: 12-01-2025
A6: 305 | B6: North | C6: Amit | D6: Mobile | E6: 4 | F6: 15000 | G6: 15-01-2025
A7: 306 | B7: South | C7: Riya | D7: Laptop | E7: 2 | F7: 45000 | G7: 18-01-2025

Sheet Product_Master
A1: Product | B1: Category | C1: GST_%
A2: Laptop | B2: Electronics | C2: 18
A3: Mobile | B3: Electronics | C3: 12
A4: Tablet | B4: Electronics | C4: 12

Sheet Student_Marks
A1: Student_ID | B1: Name | C1: Maths | D1: Statistics | E1: Excel | F1: Attendance_%
A2: 1 | B2: Rahul | C2: 78 | D2: 82 | E2: 85 | F2: 92
A3: 2 | B3: Sneha | C3: 88 | D3: 91 | E3: 90 | F3: 96
A4: 3 | B4: Arjun | C4: 65 | D4: 70 | E4: 72 | F4: 85
A5: 4 | B5: Pooja | C5: 92 | D5: 89 | E5: 94 | F5: 98
A6: 5 | B6: Vikas | C6: 55 | D6: 60 | E6: 58 | F6: 80

Sheet Questions
A1: 1. Calculate Total Sales for each order (Quantity × Unit_Price). | J1: 2
A2: 2. Calculate GST Amount using VLOOKUP from Product_Master. | J2: 2
A3: 3. Find Final Amount payable (Total Sales + GST). | J3: 2
A4: 4. Find Grand Total of Final Amount. | J4: 2
A5: 5. Count total number of orders using COUNTA. | J5: 2
A6: 6. Find Region-wise total sales using SUMIF. | J6: 2
A7: 7. Use IF to classify Quantity as High (>3) or Low (<=3). | J7: 2
A8: 8. Find the maximum and minimum Final Amount. | J8: 2
A9: 9. Extract month name from Sales_Date. | J9: 2
A10: 10. Sort Sales_Data by Final Amount (Descending). | J10: 2
A11: 11. Use INDEX-MATCH to fetch Product Category. | J11: 2
A12: 12. Calculate average marks of each student. | J12: 2
... A30: 30. Protect the Student_Marks sheet. | J30: 2
J32: =SUM(J1:J30) -> 60

Sheet Answers
A1: 1. Calculate Total Sales for each order (Quantity × Unit_Price).
B3: Order_ID | C3: Region | D3: Salesperson | E3: Product | F3: Quantity | G3: Unit_Price | H3: Sales_Date | I3: Total Sales
B4: 301 | C4: North | D4: Amit | E4: Laptop | F4: 2 | G4: 45000 | H4: 05-01-2025 | I4: =F4*G4 -> 90000
B5: 302 | C5: South | D5: Riya | E5: Mobile | F5: 5 | G5: 15000 | H5: 07-01-2025 | I5: =F5*G5 -> 75000
B6: 303 | C6: East | D6: Kunal | E6: Tablet | F6: 3 | G6: 18000 | H6: 10-01-2025 | I6: =F6*G6 -> 54000
B7: 304 | C7: West | D7: Neha | E7: Laptop | F7: 1 | G7: 45000 | H7: 12-01-2025 | I7: =F7*G7 -> 45000
B8: 305 | C8: North | D8: Amit | E8: Mobile | F8: 4 | G8: 15000 | H8: 15-01-2025 | I8: =F8*G8 -> 60000
B9: 306 | C9: South | D9: Riya | E9: Laptop | F9: 2 | G9: 45000 | H9: 18-01-2025 | I9: =F9*G9 -> 90000
A11: 2. Calculate GST Amount using VLOOKUP from Product_Master.
B13: Order_ID | C13: Region | D13: Salesperson | E13: Product | F13: Quantity | G13: Unit_Price | H13: Sales_Date | I13: Total Sales | J13: GST% | K13: GST Amount
B14: 301 | C14: North | D14: Amit | E14: Laptop | F14: 2 | G14: 45000 | H14: 05-01-2025 | I14: =F14*G14 -> 90000 | J14: =VLOOKUP(E14,Product_Master!A:C,3,0) -> 18 | K14: =I14*J14/100 -> 16200
B15: 302 | C15: South | D15: Riya | E15: Mobile | F15: 5 | G15: 15000 | H15: 07-01-2025 | I15: =F15*G15 -> 75000 | J15: =VLOOKUP(E15,Product_Master!A:C,3,0) -> 12 | K15: =I15*J15/100 -> 9000
B16: 303 | C16: East | D16: Kunal | E16: Tablet | F16: 3 | G16: 18000 | H16: 10-01-2025 | I16: =F16*G16 -> 54000 | J16: =VLOOKUP(E16,Product_Master!A:C,3,0) -> 12 | K16: =I16*J16/100 -> 6480
B17: 304 | C17: West | D17: Neha | E17: Laptop | F17: 1 | G17: 45000 | H17: 12-01-2025 | I17: =F17*G17 -> 45000 | J17: =VLOOKUP(E17,Product_Master!A:C,3,0) -> 18 | K17: =I17*J17/100 -> 8100
B18: 305 | C18: North | D18: Amit | E18: Mobile | F18: 4 | G18: 15000 | H18: 15-01-2025 | I18: =F18*G18 -> 60000 | J18: =VLOOKUP(E18,Product_Master!A:C,3,0) -> 12 | K18: =I18*J18/100 -> 7200
B19: 306 | C19: South | D19: Riya | E19: Laptop | F19: 2 | G19: 45000 | H19: 18-01-2025 | I19: =F19*G19 -> 90000 | J19: =VLOOKUP(E19,Product_Master!A:C,3,0) -> 18 | K19: =I19*J19/100 -> 16200
A21: 3. Find Final Amount payable (Total Sales + GST).
B23: Order_ID | C23: Region | D23: Salesperson | E23: Product | F23: Quantity | G23: Unit_Price | H23: Sales_Date | I23: Total Sales | J23: GST% | K23: GST Amount | L23: Final Payable Amount
B24: 301 | C24: North | D24: Amit | E24: Laptop | F24: 2 | G24: 45000 | H24: 05-01-2025 | I24: =F24*G24 -> 90000 | J24: =VLOOKUP(E24,Product_Master!A:C,3,0) -> 18 | K24: =I24*J24/100 -> 16200 | L24: =I24+K24 -> 106200
B25: 302 | C25: South | D25: Riya | E25: Mobile | F25: 5 | G25: 15000 | H25: 07-01-2025 | I25: =F25*G25 -> 75000 | J25: =VLOOKUP(E25,Product_Master!A:C,3,0) -> 12 | K25: =I25*J25/100 -> 9000 | L25: =I25+K25 -> 84000
B26: 303 | C26: East | D26: Kunal | E26: Tablet | F26: 3 | G26: 18000 | H26: 10-01-2025 | I26: =F26*G26 -> 54000 | J26: =VLOOKUP(E26,Product_Master!A:C,3,0) -> 12 | K26: =I26*J26/100 -> 6480 | L26: =I26+K26 -> 60480
B27: 304 | C27: West | D27: Neha | E27: Laptop | F27: 1 | G27: 45000 | H27: 12-01-2025 | I27: =F27*G27 -> 45000 | J27: =VLOOKUP(E27,Product_Master!A:C,3,0) -> 18 | K27: =I27*J27/100 -> 8100 | L27: =I27+K27 -> 53100
B28: 305 | C28: North | D28: Amit | E28: Mobile | F28: 4 | G28: 15000 | H28: 15-01-2025 | I28: =F28*G28 -> 60000 | J28: =VLOOKUP(E28,Product_Master!A:C,3,0) -> 12 | K28: =I28*J28/100 -> 7200 | L28: =I28+K28 -> 67200
B29: 306 | C29: South | D29: Riya | E29: Laptop | F29: 2 | G29: 45000 | H29: 18-01-2025 | I29: =F29*G29 -> 90000 | J29: =VLOOKUP(E29,Product_Master!A:C,3,0) -> 18 | K29: =I29*J29/100 -> 16200 | L29: =I29+K29 -> 106200
A31: 4. Find Grand Total of Final Amount
B33: Order_ID | C33: Region | D33: Salesperson | E33: Product | F33: Quantity | G33: Unit_Price | H33: Sales_Date | I33: Total Sales | J33: GST% | K33: GST Amount | L33: Final Payable Amount
B34: 301 | C34: North | D34: Amit | E34: Laptop | F34: 2 | G34: 45000 | H34: 05-01-2025 | I34: =F34*G34 -> 90000 | J34: =VLOOKUP(E34,Product_Master!A:C,3,0) -> 18 | K34: =I34*J34/100 -> 16200 | L34: =I34+K34 -> 106200
B35: 302 | C35: South | D35: Riya | E35: Mobile | F35: 5 | G35: 15000 | H35: 07-01-2025 | I35: =F35*G35 -> 75000 | J35: =VLOOKUP(E35,Product_Master!A:C,3,0) -> 12 | K35: =I35*J35/100 -> 9000 | L35: =I35+K35 -> 84000
B36: 303 | C36: East | D36: Kunal | E36: Tablet | F36: 3 | G36: 18000 | H36: 10-01-2025 | I36: =F36*G36 -> 54000 | J36: =VLOOKUP(E36,Product_Master!A:C,3,0) -> 12 | K36: =I36*J36/100 -> 6480 | L36: =I36+K36 -> 60480
B37: 304 | C37: West | D37: Neha | E37: Laptop | F37: 1 | G37: 45000 | H37: 12-01-2025 | I37: =F37*G37 -> 45000 | J37: =VLOOKUP(E37,Product_Master!A:C,3,0) -> 18 | K37: =I37*J37/100 -> 8100 | L37: =I37+K37 -> 53100
B38: 305 | C38: North | D38: Amit | E38: Mobile | F38: 4 | G38: 15000 | H38: 15-01-2025 | I38: =F38*G38 -> 60000 | J38: =VLOOKUP(E38,Product_Master!A:C,3,0) -> 12 | K38: =I38*J38/100 -> 7200 | L38: =I38+K38 -> 67200
B39: 306 | C39: South | D39: Riya | E39: Laptop | F39: 2 | G39: 45000 | H39: 18-01-2025 | I39: =F39*G39 -> 90000 | J39: =VLOOKUP(E39,Product_Master!A:C,3,0) -> 18 | K39: =I39*J39/100 -> 16200 | L39: =I39+K39 -> 106200
L40: =SUM(L34:L39) -> 477180
A42: 5. Count total number of orders using COUNTA
A44: Total number of orders | B44: =COUNTA(Sales_Data!A2:A8) -> 6
A46: 6. Find Region-wise total sales using SUMIF
B48: Order_ID | C48: Region | D48: Salesperson | E48: Product | F48: Quantity | G48: Unit_Price | H48: Sales_Date | I48: Total Sales | L48: Region | M48: Total Sales
B49: 301 | C49: North | D49: Amit | E49: Laptop | F49: 2 | G49: 45000 | H49: 05-01-2025 | I49: =F49*G49 -> 90000 | L49: North | M49: =SUMIF(C49:C54,L49,I49:I54) -> 150000
B50: 302 | C50: South | D50: Riya | E50: Mobile | F50: 5 | G50: 15000 | H50: 07-01-2025 | I50: =F50*G50 -> 75000 | L50: South | M50: =SUMIF(C50:C55,L50,I50:I55) -> 165000
B51: 303 | C51: East | D51: Kunal | E51: Tablet | F51: 3 | G51: 18000 | H51: 10-01-2025 | I51: =F51*G51 -> 54000 | L51: East | M51: =SUMIF(C51:C56,L51,I51:I56) -> 54000
B52: 304 | C52: West | D52: Neha | E52: Laptop | F52: 1 | G52: 45000 | H52: 12-01-2025 | I52: =F52*G52 -> 45000 | L52: West | M52: =SUMIF(C52:C57,L52,I52:I57) -> 45000
B53: 305 | C53: North | D53: Amit | E53: Mobile | F53: 4 | G53: 15000 | H53: 15-01-2025 | I53: =F53*G53 -> 60000
B54: 306 | C54: South | D54: Riya | E54: Laptop | F54: 2 | G54: 45000 | H54: 18-01-2025 | I54: =F54*G54 -> 90000
A56: 7. Use IF to classify Quantity as High (>3) or Low (<=3).
B58: Order_ID | C58: Region | D58: Salesperson | E58: Product | F58: Quantity | G58: Unit_Price | H58: Sales_Date | I58: Quantity classification
B59: 301 | C59: North | D59: Amit | E59: Laptop | F59: 2 | G59: 45000 | H59: 05-01-2025 | I59: =IF(Answers!F59>3, "High", "Low") -> Low
B60: 302 | C60: South | D60: Riya | E60: Mobile | F60: 5 | G60: 15000 | H60: 07-01-2025 | I60: =IF(Answers!F60>3, "High", "Low") -> High
B61: 303 | C61: East | D61: Kunal | E61: Tablet | F61: 3 | G61: 18000 | H61: 10-01-2025 | I61: =IF(Answers!F61>3, "High", "Low") -> Low
B62: 304 | C62: West | D62: Neha | E62: Laptop | F62: 1 | G62: 45000 | H62: 12-01-2025 | I62: =IF(Answers!F62>3, "High", "Low") -> Low
B63: 305 | C63: North | D63: Amit | E63: Mobile | F63: 4 | G63: 15000 | H63: 15-01-2025 | I63: =IF(Answers!F63>3, "High", "Low") -> High
B64: 306 | C64: South | D64: Riya | E64: Laptop | F64: 2 | G64: 45000 | H64: 18-01-2025 | I64: =IF(Answers!F64>3, "High", "Low") -> Low
A66: 8. Find the maximum and minimum Final Amount.
B68: Order_ID | C68: Region | D68: Salesperson | E68: Product | F68: Quantity | G68: Unit_Price | H68: Sales_Date | I68: Total Sales | J68: GST% | K68: GST Amount | L68: Final Payable Amount
B69: 301 | C69: North | D69: Amit | E69: Laptop | F69: 2 | G69: 45000 | H69: 05-01-2025 | I69: =F69*G69 -> 90000 | J69: =VLOOKUP(E69,Product_Master!A:C,3,0) -> 18 | K69: =I69*J69/100 -> 16200 | L69: =I69+K69 -> 106200
B70: 302 | C70: South | D70: Riya | E70: Mobile | F70: 5 | G70: 15000 | H70: 07-01-2025 | I70: =F70*G70 -> 75000 | J70: =VLOOKUP(E70,Product_Master!A:C,3,0) -> 12 | K70: =I70*J70/100 -> 9000 | L70: =I70+K70 -> 84000
B71: 303 | C71: East | D71: Kunal | E71: Tablet | F71: 3 | G71: 18000 | H71: 10-01-2025 | I71: =F71*G71 -> 54000 | J71: =VLOOKUP(E71,Product_Master!A:C,3,0) -> 12 | K71: =I71*J71/100 -> 6480 | L71: =I71+K71 -> 60480
B72: 304 | C72: West | D72: Neha | E72: Laptop | F72: 1 | G72: 45000 | H72: 12-01-2025 | I72: =F72*G72 -> 45000 | J72: =VLOOKUP(E72,Product_Master!A:C,3,0) -> 18 | K72: =I72*J72/100 -> 8100 | L72: =I72+K72 -> 53100
B73: 305 | C73: North | D73: Amit | E73: Mobile | F73: 4 | G73: 15000 | H73: 15-01-2025 | I73: =F73*G73 -> 60000 | J73: =VLOOKUP(E73,Product_Master!A:C,3,0) -> 12 | K73: =I73*J73/100 -> 7200 | L73: =I73+K73 -> 67200
B74: 306 | C74: South | D74: Riya | E74: Laptop | F74: 2 | G74: 45000 | H74: 18-01-2025 | I74: =F74*G74 -> 90000 | J74: =VLOOKUP(E74,Product_Master!A:C,3,0) -> 18 | K74: =I74*J74/100 -> 16200 | L74: =I74+K74 -> 106200
B76: Maximum | C76: Minimum
B77: =MAX(L69:L74) -> 106200 | C77: =MIN(L69:L74) -> 53100
A79: 9. Extract month name from Sales_Date.
B81: Order_ID | C81: Region | D81: Salesperson | E81: Product | F81: Quantity | G81: Unit_Price | H81: Sales_Date | I81: Month name
B82: 301 | C82: North | D82: Amit | E82: Laptop | F82: 2 | G82: 45000 | H82: 05-01-2025 | I82: =TEXT(H82,"MMMM") -> January
B83: 302 | C83: South | D83: Riya | E83: Mobile | F83: 5 | G83: 15000 | H83: 07-01-2025 | I83: =TEXT(H83,"MMMM") -> January
B84: 303 | C84: East | D84: Kunal | E84: Tablet | F84: 3 | G84: 18000 | H84: 10-01-2025 | I84: =TEXT(H84,"MMMM") -> January
B85: 304 | C85: West | D85: Neha | E85: Laptop | F85: 1 | G85: 45000 | H85: 12-01-2025 | I85: =TEXT(H85,"MMMM") -> January
B86: 305 | C86: North | D86: Amit | E86: Mobile | F86: 4 | G86: 15000 | H86: 15-01-2025 | I86: =TEXT(H86,"MMMM") -> January
B87: 306 | C87: South | D87: Riya | E87: Laptop | F87: 2 | G87: 45000 | H87: 18-01-2025 | I87: =TEXT(H87,"MMMM") -> January
A89: 10. Sort Sales_Data by Final Amount (Descending).
B91: Order_ID | C91: Region | D91: Salesperson | E91: Product | F91: Quantity | G91: Unit_Price | H91: Sales_Date | I91: Total Sales | J91: GST% | K91: GST Amount | L91: Final Payable Amount
B92: 301 | C92: North | D92: Amit | E92: Laptop | F92: 2 | G92: 45000 | H92: 05-01-2025 | I92: =F92*G92 -> 90000 | J92: =VLOOKUP(E92,Product_Master!A:C,3,0) -> 18 | K92: =I92*J92/100 -> 16200 | L92: =I92+K92 -> 106200
B93: 306 | C93: South | D93: Riya | E93: Laptop | F93: 2 | G93: 45000 | H93: 18-01-2025 | I93: =F93*G93 -> 90000 | J93: =VLOOKUP(E93,Product_Master!A:C,3,0) -> 18 | K93: =I93*J93/100 -> 16200 | L93: =I93+K93 -> 106200
B94: 302 | C94: South | D94: Riya | E94: Mobile | F94: 5 | G94: 15000 | H94: 07-01-2025 | I94: =F94*G94 -> 75000 | J94: =VLOOKUP(E94,Product_Master!A:C,3,0) -> 12 | K94: =I94*J94/100 -> 9000 | L94: =I94+K94 -> 84000
B95: 305 | C95: North | D95: Amit | E95: Mobile | F95: 4 | G95: 15000 | H95: 15-01-2025 | I95: =F95*G95 -> 60000 | J95: =VLOOKUP(E95,Product_Master!A:C,3,0) -> 12 | K95: =I95*J95/100 -> 7200 | L95: =I95+K95 -> 67200
B96: 303 | C96: East | D96: Kunal | E96: Tablet | F96: 3 | G96: 18000 | H96: 10-01-2025 | I96: =F96*G96 -> 54000 | J96: =VLOOKUP(E96,Product_Master!A:C,3,0) -> 12 | K96: =I96*J96/100 -> 6480 | L96: =I96+K96 -> 60480
B97: 304 | C97: West | D97: Neha | E97: Laptop | F97: 1 | G97: 45000 | H97: 12-01-2025 | I97: =F97*G97 -> 45000 | J97: =VLOOKUP(E97,Product_Master!A:C,3,0) -> 18 | K97: =I97*J97/100 -> 8100 | L97: =I97+K97 -> 53100
A99: 11. Use INDEX-MATCH to fetch Product Category.
A109: 12. Calculate average marks of each student.
B111: Student_ID | C111: Name | D111: Maths | E111: Statistics | F111: Excel | G111: Attendance_% | H111: Average Marks
B112: 1 | C112: Rahul | D112: 78 | E112: 82 | F112: 85 | G112: 92 | H112: =AVERAGE(D112:F112) -> 81.666667
B113: 2 | C113: Sneha | D113: 88 | E113: 91 | F113: 90 | G113: 96 | H113: =AVERAGE(D113:F113) -> 89.666667
B114: 3 | C114: Arjun | D114: 65 | E114: 70 | F114: 72 | G114: 85 | H114: =AVERAGE(D114:F114) -> 69
B115: 4 | C115: Pooja | D115: 92 | E115: 89 | F115: 94 | G115: 98 | H115: =AVERAGE(D115:F115) -> 91.666667
B116: 5 | C116: Vikas | D116: 55 | E116: 60 | F116: 58 | G116: 80 | H116: =AVERAGE(D116:F116) -> 57.666667
A118: 13. Find the topper based on average marks.
B120: Student_ID | C120: Name | D120: Maths | E120: Statistics | F120: Excel | G120: Attendance_% | H120: Average Marks
B121: 1 | C121: Rahul | D121: 78 | E121: 82 | F121: 85 | G121: 92 | H121: =AVERAGE(D121:F121) -> 81.666667
B122: 2 | C122: Sneha | D122: 88 | E122: 91 | F122: 90 | G122: 96 | H122: =AVERAGE(D122:F122) -> 89.666667
B123: 3 | C123: Arjun | D123: 65 | E123: 70 | F123: 72 | G123: 85 | H123: =AVERAGE(D123:F123) -> 69
B124: 4 | C124: Pooja | D124: 92 | E124: 89 | F124: 94 | G124: 98 | H124: =AVERAGE(D124:F124) -> 91.666667
B125: 5 | C125: Vikas | D125: 55 | E125: 60 | F125: 58 | G125: 80 | H125: =AVERAGE(D125:F125) -> 57.666667
A127: 14. Count students with Attendance above 90%.
B129: Student_ID | C129: Name | D129: Maths | E129: Statistics | F129: Excel | G129: Attendance_%
B130: 1 | C130: Rahul | D130: 78 | E130: 82 | F130: 85 | G130: 92
B131: 2 | C131: Sneha | D131: 88 | E131: 91 | F131: 90 | G131: 96
B132: 3 | C132: Arjun | D132: 65 | E132: 70 | F132: 72 | G132: 85
B133: 4 | C133: Pooja | D133: 92 | E133: 89 | F133: 94 | G133: 98
B134: 5 | C134: Vikas | D134: 55 | E134: 60 | F134: 58 | G134: 80
